xpatch/__init__.py
xpatch/__init__.pyi
xpatch/py.typed
xpatch/xpatch.cpython-313-x86_64-linux-gnu.so
xpatch_rs-0.3.1.dist-info/METADATA
xpatch_rs-0.3.1.dist-info/WHEEL
xpatch_rs-0.3.1.dist-info/RECORD
