Metadata-Version: 2.4
Name: xpatch-rs
Version: 0.3.1
Classifier: Programming Language :: Rust
Classifier: Programming Language :: Python :: Implementation :: CPython
Classifier: Programming Language :: Python :: Implementation :: PyPy
Classifier: Programming Language :: Python :: 3
Classifier: Programming Language :: Python :: 3.8
Classifier: Programming Language :: Python :: 3.9
Classifier: Programming Language :: Python :: 3.10
Classifier: Programming Language :: Python :: 3.11
Classifier: Programming Language :: Python :: 3.12
Classifier: Programming Language :: Python :: 3.13
Classifier: License :: OSI Approved :: GNU Affero General Public License v3 or later (AGPLv3+)
Classifier: Topic :: System :: Archiving :: Compression
Summary: High-performance delta compression library with automatic algorithm selection
Keywords: delta,compression,diff,patch,version-control
Home-Page: https://github.com/ImGajeed76/xpatch
Author: ImGajeed76
License: AGPL-3.0-or-later
Requires-Python: >=3.8
Project-URL: Homepage, https://github.com/ImGajeed76/xpatch
Project-URL: Repository, https://github.com/ImGajeed76/xpatch
Project-URL: Documentation, https://github.com/ImGajeed76/xpatch#readme
